ferrous-0.2.1.dist-info/METADATA
ferrous-0.2.1.dist-info/WHEEL
ferrous-0.2.1.dist-info/licenses/LICENSE
ferrous/__init__.py
ferrous/_ferrous.pypy311-pp73-aarch64-linux-gnu.so
ferrous-0.2.1.dist-info/RECORD
