Metadata-Version: 2.4
Name: ferrous
Version: 0.2.1
Classifier: Programming Language :: Rust
Classifier: Programming Language :: Python :: 3
Classifier: Programming Language :: Python :: Implementation :: CPython
Classifier: Topic :: Scientific/Engineering :: Artificial Intelligence
Classifier: License :: OSI Approved :: MIT License
License-File: LICENSE
Summary: High-performance RAG primitives in Rust
Keywords: rag,rust,llm,search,cache,embeddings
Author: Mann Patel
License: MIT
Requires-Python: >=3.8
Project-URL: Homepage, https://github.com/mannrp/ferrous
Project-URL: Repository, https://github.com/mannrp/ferrous
